ldplayer/__init__.py
ldplayer/ldplayer.py
ldplayer-1.0.0.dist-info/LICENSE
ldplayer-1.0.0.dist-info/METADATA
ldplayer-1.0.0.dist-info/WHEEL
ldplayer-1.0.0.dist-info/top_level.txt
ldplayer-1.0.0.dist-info/RECORD
