Metadata-Version: 2.1
Name: ldplayer
Version: 1.0.0
Summary: This is a package for LDPlayer emulator control software. (unofficial)
Home-page: https://github.com/sinmentis/ldplayer
Author: sinmentis
Maintainer: sinmentis
License-File: LICENSE
